{
    "fluentMethods": true,
    "relationships": [
        {
            "relationshipName": "profile",
            "otherEntityName": "profile",
            "relationshipType": "many-to-one",
            "otherEntityField": "id"
        }
    ],
    "fields": [
        {
            "fieldName": "rating",
            "fieldType": "Integer",
            "fieldValidateRules": [
                "required"
            ]
        },
        {
            "fieldName": "comments",
            "fieldType": "byte[]",
            "fieldTypeBlobContent": "text",
            "fieldValidateRules": [
                "required"
            ]
        },
        {
            "fieldName": "createdDate",
            "fieldType": "LocalDate",
            "fieldValidateRules": [
                "required"
            ]
        },
        {
            "fieldName": "userId",
            "fieldType": "Long",
            "fieldValidateRules": [
                "required"
            ]
        }
    ],
    "changelogDate": "20171203053656",
    "entityTableName": "review",
    "dto": "mapstruct",
    "pagination": "pagination",
    "service": "serviceImpl",
    "jpaMetamodelFiltering": false,
    "microserviceName": "profile"
}